verilog/Cordic1.v
/*
 * Cordic1.v - Implementation of a 2.16 Cordic Processor
 * Co-Ordinate Rotational by DIgital Computer
 * Student Names: Charlie Gorey O'Neill, Emmett Lawlor, Niall Coughlan, Cian Surlis, Ciaran Hogan
 * Id: 18222803, 18238831, 16154355 , 18233074, 18238831
 */

module CORDIC(output signed[1:-16] cosine,
	      output signed [1:-16] sine,
	      output signed [1:-16] angle,
	      output 		    done,
	      input signed [1:-16]  target_angle,
	      input 		    init, 
	      input 		    clk);

   reg signed [1:-16] 		    current_ang, delta_ang, new_ang, cos, sin, new_cos, new_sin;
   reg [3:0] 			    cycle;
   reg 				    state;
   
   // Create angle step look up table, can have up to 2^18 (262,144) steps, to be calculated externally and
   // then introduced to the program as constants
   // Delta Angle values are scaled by 2^16 so to ensure integer arithmetic up to 16 decimal places.

   always @(*)
     begin
	case(cycle)
	  
	  0: delta_ang = 18'H0C910;
	  1: delta_ang = 18'H076B2; 
	  2: delta_ang = 18'H03EB7;
	  3: delta_ang = 18'H00FFB; 
	  4: delta_ang = 18'H01FD6; 
	  5: delta_ang = 18'H007FF; 
	  6: delta_ang = 18'H00400; 
	  7: delta_ang = 18'H00200; 
	  8: delta_ang = 18'H00100;
	  9: delta_ang = 18'H00080; 
	  10: delta_ang = 18'H00040;
	  11: delta_ang = 18'H00020;
	  12: delta_ang = 18'H00010; 
	  13: delta_ang = 18'H00008;
	  14: delta_ang = 18'h00004;
	  15: delta_ang = 18'h00002;
	  16: delta_ang = 18'h00001; 

	endcase
     end

   always @(posedge clk)
     begin
	if( init == 1'b1 ) begin
	   state <= 0;
	   cycle <= 0;
	   current_ang <= 0;
	   cos <= 18'h09b75; 	// This is constant K which initializes cosine.
	   sin <= 0;
	end
	else begin
	   if ( state == 0 ) begin
	      if ( cycle == 15) begin 
		 state <= 1;
	      end
	      cos <= new_cos;
	      sin <= new_sin;
	      current_ang <= new_ang;
	      cycle <= cycle + 1;
	   end
	end
     end
// Here is the cordic processing algorithm at work
   always @(*)
	begin
	    if ( target_angle >= angle ) begin
		new_ang <= current_ang + delta_ang;	
	   	new_cos <= cos - (sin >>> cycle);
	        new_sin <= sin + (cos >>> cycle);
		    end
	else begin 
		new_ang <= current_ang - delta_ang;
		new_cos <= cos + (sin >>> cycle);
		new_sin <= sin - (cos >>> cycle);
	 end
end
   assign done = state;
   assign cosine = cos;
   assign sine = sin;
   assign angle = current_ang;

endmodule

verilog/cordic_tb.v
// Test bench for Cordic
// Tests for +- angles 
// Edge cases are +-90 and 0 degrees
// Student Names: Charlie Gorey O'Neill, Emmett Lawlor, Niall Coughlan, Cian Surlis, Ciaran Hogan
// Id: 18222803, 18238831, 16154355 ,18233074, 18238831
`timescale 1ns/1ps

module cordic_tb;
   reg signed[1:-16] angle_in;
   wire signed [1:-16] cos_out, sin_out, angle_out;
   wire 	       done;
   reg 		       clk, init;
   integer 	       count;

   task run_cordic(input signed[1:-16] angle);
      begin
	 $display("test for input angle %d (%15.12f rads, %10.6f degs)", angle, angle/65536.0, angle*0.0008742642137616321); // Displays input angle in in 2.16, radians and degrees
	 clk = 0;
	 init = 0;
	 angle_in = angle;
	 #5 init = 1;
	 count = 0;
	 #5 clk = 1;
	 #5 init = 0;
	 #5 clk = 0;		
	 while ( done == 1'b0 ) begin
	    #5 clk = 1;
	    #10 clk = 0;
	    #5 count = count+1;
	    init = 0;
	 end
	 #5 $display("%6t: %3d: init %1b, done %1b, angle %18b, cos %18b, sin %18b",
		     $time, count, init, done, angle_out, cos_out, sin_out);
	 $display("angle %d (%15.12f), cos %d (%15.12f) sin %d (%15.12f)", 
		  angle_out, angle_out/65536.0, cos_out, cos_out/65536.0, sin_out, sin_out/65536.0);
      end
   endtask

   task run_display(input signed[1:-16] angle, input integer expected_angle, input integer expected_cosine, input integer expected_sine);
      begin
	 run_cordic(angle);
	 $display("Results should be: angle: %d, cosine: %d, sine: %d\n\n", expected_angle, expected_cosine, expected_sine);
      end
   endtask

   // dut - device under test
   CORDIC dut(cos_out, sin_out, angle_out, done, angle_in, init, clk);

   initial
     begin
	// Tests 4 arguments: 1-Input angle, 2-Expected out angle, 3-Expected Cos, 4-Expected Sine. 
	// All arguments presented in 2.16 rads

	#0 run_display(0, -1, 65536, 2);
	#100 run_display(102944, 102945, 2, 65536); // 102944 = pi/2 radians (90 deg) in 2.16 fp format

	#100 run_display(51472, 51473, 46341, 46342); //"		" = pi/4 

	#100 run_display(25736, 25737, 60546, 25081); //"		" = pi/8 

	#100 run_display(77208, 77207, 25081, 60546); //"		" = 3*pi/8 

	#100 run_display(-102944, -102945, -2, -65536); //"		" = -pi/2 

	#100 run_display(-51472, -51471, 46343, -46342); //"		" = -pi/4 

     end

   initial
     begin
	$dumpfile("Cordic1.vcd");
	$dumpvars;
     end
endmodule

Cordic1.vcd
$date
	Fri Apr  1 15:18:02 2022
$end
$version
	Icarus Verilog
$end
$timescale
	1ps
$end
$scope module cordic_tb $end
$var wire 18 ! sin_out [1:-16] $end
$var wire 1 " done $end
$var wire 18 # cos_out [1:-16] $end
$var wire 18 $ angle_out [1:-16] $end
$var reg 18 % angle_in [1:-16] $end
$var reg 1 & clk $end
$var reg 1 ' init $end
$var integer 32 ( count [31:0] $end
$scope module dut $end
$var wire 18 ) angle [1:-16] $end
$var wire 1 & clk $end
$var wire 18 * cosine [1:-16] $end
$var wire 1 " done $end
$var wire 1 ' init $end
$var wire 18 + sine [1:-16] $end
$var wire 18 , target_angle [1:-16] $end
$var reg 18 - cos [1:-16] $end
$var reg 18 . current_ang [1:-16] $end
$var reg 4 / cycle [3:0] $end
$var reg 18 0 delta_ang [1:-16] $end
$var reg 18 1 new_ang [1:-16] $end
$var reg 18 2 new_cos [1:-16] $end
$var reg 18 3 new_sin [1:-16] $end
$var reg 18 4 sin [1:-16] $end
$var reg 1 5 state $end
$upscope $end
$scope task run_cordic $end
$var reg 18 6 angle [1:-16] $end
$upscope $end
$scope task run_display $end
$var reg 18 7 angle [1:-16] $end
$var integer 32 8 expected_angle [31:0] $end
$var integer 32 9 expected_cosine [31:0] $end
$var integer 32 : expected_sine [31:0] $end
$upscope $end
$upscope $end
$enddefinitions $end
#0
$dumpvars
b10 :
b10000000000000000 9
b11111111111111111111111111111111 8
b0 7
b0 6
x5
bx 4
bx 3
bx 2
bx 1
bx 0
bx /
bx .
bx -
b0 ,
bx +
bx *
bx )
bx (
0'
0&
b0 %
bx $
bx #
x"
bx !
$end
#5000
b0 (
1'
#10000
b110110010010001011 3
b1001101101110101 2
b1100100100010000 1
b1100100100010000 0
b0 !
b0 +
b0 4
b1001101101110101 #
b1001101101110101 *
b1001101101110101 -
b0 $
b0 )
b0 .
b0 /
0"
05
1&
#15000
0'
#20000
0&
#25000
b111011010110010 0
b1 /
b1100100100010000 $
b1100100100010000 )
b1100100100010000 .
b110110010010001011 !
b110110010010001011 +
b110110010010001011 4
1&
#35000
0&
#40000
b1 (
#45000
b11111010110111 0
b10 /
1&
#55000
0&
#60000
b10 (
#65000
b111111111011 0
b11 /
1&
#75000
0&
#80000
b11 (
#85000
b1111111010110 0
b100 /
1&
#95000
0&
#100000
b100 (
#105000
b11111111111 0
b101 /
1&
#115000
0&
#120000
b101 (
#125000
b10000000000 0
b110 /
1&
#135000
0&
#140000
b110 (
#145000
b1000000000 0
b111 /
1&
#155000
0&
#160000
b111 (
#165000
b100000000 0
b1000 /
1&
#175000
0&
#180000
b1000 (
#185000
b10000000 0
b1001 /
1&
#195000
0&
#200000
b1001 (
#205000
b1000000 0
b1010 /
1&
#215000
0&
#220000
b1010 (
#225000
b100000 0
b1011 /
1&
#235000
0&
#240000
b1011 (
#245000
b10000 0
b1100 /
1&
#255000
0&
#260000
b1100 (
#265000
b1000 0
b1101 /
1&
#275000
0&
#280000
b1101 (
#285000
b100 0
b1110 /
1&
#295000
0&
#300000
b1110 (
#305000
b10 0
b1111 /
1&
#315000
0&
#320000
b1111 (
#325000
b1100100100010000 0
b0 /
1"
15
1&
#335000
0&
#340000
b10000 (
#445000
b101100100100010110 3
b10011011011101010 2
b11001001000100000 1
b11001001000100000 %
b11001001000100000 ,
b11001001000100000 6
b10000000000000000 :
b10 9
b11001001000100001 8
b11001001000100000 7
#450000
b0 (
1'
#455000
b110110010010001011 3
b1001101101110101 2
b1100100100010000 1
b0 !
b0 +
b0 4
b0 $
b0 )
b0 .
0"
05
1&
#460000
0'
#465000
0&
#470000
b110001011011010001 3
b1110100100110000 2
b10011111111000010 1
b111011010110010 0
b1 /
b1100100100010000 $
b1100100100010000 )
b1100100100010000 .
b110110010010001011 !
b110110010010001011 +
b110110010010001011 4
1&
#480000
0&
#485000
b1 (
#490000
b101101110010000101 3
b10010001101111100 2
b10111111001111001 1
b11111010110111 0
b10 /
b10011111111000010 $
b10011111111000010 )
b10011111111000010 .
b110001011011010001 !
b110001011011010001 +
b110001011011010001 4
b1110100100110000 #
b1110100100110000 *
b1110100100110000 -
1&
#500000
0&
#505000
b10 (
#510000
b101011100000010110 3
b10100011111101100 2
b11000111001110100 1
b111111111011 0
b11 /
b10111111001111001 $
b10111111001111001 )
b10111111001111001 .
b101101110010000101 !
b101101110010000101 +
b101101110010000101 4
b10010001101111100 #
b10010001101111100 *
b10010001101111100 -
1&
#520000
0&
#525000
b11 (
#530000
b101010001110011000 3
b10101110001101011 2
b11010111001001010 1
b1111111010110 0
b100 /
b11000111001110100 $
b11000111001110100 )
b11000111001110100 .
b101011100000010110 !
b101011100000010110 +
b101011100000010110 4
b10100011111101100 #
b10100011111101100 *
b10100011111101100 -
1&
#540000
0&
#545000
b100 (
#550000
b11111111111 0
b101 /
b11010111001001010 $
b11010111001001010 )
b11010111001001010 .
b101010001110011000 !
b101010001110011000 +
b101010001110011000 4
b10101110001101011 #
b10101110001101011 *
b10101110001101011 -
1&
#560000
0&
#565000
b101 (
#570000
b10000000000 0
b110 /
1&
#580000
0&
#585000
b110 (
#590000
b1000000000 0
b111 /
1&
#600000
0&
#605000
b111 (
#610000
b100000000 0
b1000 /
1&
#620000
0&
#625000
b1000 (
#630000
b10000000 0
b1001 /
1&
#640000
0&
#645000
b1001 (
#650000
b1000000 0
b1010 /
1&
#660000
0&
#665000
b1010 (
#670000
b100000 0
b1011 /
1&
#680000
0&
#685000
b1011 (
#690000
b10000 0
b1100 /
1&
#700000
0&
#705000
b1100 (
#710000
b1000 0
b1101 /
1&
#720000
0&
#725000
b1101 (
#730000
b100 0
b1110 /
1&
#740000
0&
#745000
b1110 (
#750000
b10 0
b1111 /
1&
#760000
0&
#765000
b1111 (
#770000
b1100100100010000 0
b0 /
1"
15
1&
#780000
0&
#785000
b10000 (
#890000
b1100100100010000 %
b1100100100010000 ,
b1100100100010000 6
b1011010100000110 :
b1011010100000101 9
b1100100100010001 8
b1100100100010000 7
#895000
b0 (
1'
#900000
b110110010010001011 3
b1001101101110101 2
b1100100100010000 1
b0 !
b0 +
b0 4
b1001101101110101 #
b1001101101110101 *
b1001101101110101 -
b0 $
b0 )
b0 .
0"
05
1&
#905000
0'
#910000
0&
#915000
b110001011011010001 3
b1110100100110000 2
b10011111111000010 1
b111011010110010 0
b1 /
b1100100100010000 $
b1100100100010000 )
b1100100100010000 .
b110110010010001011 !
b110110010010001011 +
b110110010010001011 4
1&
#925000
0&
#930000
b1 (
#935000
b11111010110111 0
b10 /
b10011111111000010 $
b10011111111000010 )
b10011111111000010 .
b110001011011010001 !
b110001011011010001 +
b110001011011010001 4
b1110100100110000 #
b1110100100110000 *
b1110100100110000 -
1&
#945000
0&
#950000
b10 (
#955000
b111111111011 0
b11 /
1&
#965000
0&
#970000
b11 (
#975000
b1111111010110 0
b100 /
1&
#985000
0&
#990000
b100 (
#995000
b11111111111 0
b101 /
1&
#1005000
0&
#1010000
b101 (
#1015000
b10000000000 0
b110 /
1&
#1025000
0&
#1030000
b110 (
#1035000
b1000000000 0
b111 /
1&
#1045000
0&
#1050000
b111 (
#1055000
b100000000 0
b1000 /
1&
#1065000
0&
#1070000
b1000 (
#1075000
b10000000 0
b1001 /
1&
#1085000
0&
#1090000
b1001 (
#1095000
b1000000 0
b1010 /
1&
#1105000
0&
#1110000
b1010 (
#1115000
b100000 0
b1011 /
1&
#1125000
0&
#1130000
b1011 (
#1135000
b10000 0
b1100 /
1&
#1145000
0&
#1150000
b1100 (
#1155000
b1000 0
b1101 /
1&
#1165000
0&
#1170000
b1101 (
#1175000
b100 0
b1110 /
1&
#1185000
0&
#1190000
b1110 (
#1195000
b10 0
b1111 /
1&
#1205000
0&
#1210000
b1111 (
#1215000
b1100100100010000 0
b0 /
1"
15
1&
#1225000
0&
#1230000
b10000 (
#1335000
b110010010001000 %
b110010010001000 ,
b110010010001000 6
b110000111111001 :
b1110110010000010 9
b110010010001001 8
b110010010001000 7
#1340000
b0 (
1'
#1345000
b110110010010001011 3
b1001101101110101 2
b1100100100010000 1
b0 !
b0 +
b0 4
b1001101101110101 #
b1001101101110101 *
b1001101101110101 -
b0 $
b0 )
b0 .
0"
05
1&
#1350000
0'
#1355000
0&
#1360000
b111011010110010 0
b1 /
b1100100100010000 $
b1100100100010000 )
b1100100100010000 .
b110110010010001011 !
b110110010010001011 +
b110110010010001011 4
1&
#1370000
0&
#1375000
b1 (
#1380000
b11111010110111 0
b10 /
1&
#1390000
0&
#1395000
b10 (
#1400000
b111111111011 0
b11 /
1&
#1410000
0&
#1415000
b11 (
#1420000
b1111111010110 0
b100 /
1&
#1430000
0&
#1435000
b100 (
#1440000
b11111111111 0
b101 /
1&
#1450000
0&
#1455000
b101 (
#1460000
b10000000000 0
b110 /
1&
#1470000
0&
#1475000
b110 (
#1480000
b1000000000 0
b111 /
1&
#1490000
0&
#1495000
b111 (
#1500000
b100000000 0
b1000 /
1&
#1510000
0&
#1515000
b1000 (
#1520000
b10000000 0
b1001 /
1&
#1530000
0&
#1535000
b1001 (
#1540000
b1000000 0
b1010 /
1&
#1550000
0&
#1555000
b1010 (
#1560000
b100000 0
b1011 /
1&
#1570000
0&
#1575000
b1011 (
#1580000
b10000 0
b1100 /
1&
#1590000
0&
#1595000
b1100 (
#1600000
b1000 0
b1101 /
1&
#1610000
0&
#1615000
b1101 (
#1620000
b100 0
b1110 /
1&
#1630000
0&
#1635000
b1110 (
#1640000
b10 0
b1111 /
1&
#1650000
0&
#1655000
b1111 (
#1660000
b1100100100010000 0
b0 /
1"
15
1&
#1670000
0&
#1675000
b10000 (
#1780000
b101100100100010110 3
b10011011011101010 2
b11001001000100000 1
b10010110110011000 %
b10010110110011000 ,
b10010110110011000 6
b1110110010000010 :
b110000111111001 9
b10010110110010111 8
b10010110110011000 7
#1785000
b0 (
1'
#1790000
b110110010010001011 3
b1001101101110101 2
b1100100100010000 1
b0 !
b0 +
b0 4
b0 $
b0 )
b0 .
0"
05
1&
#1795000
0'
#1800000
0&
#1805000
b110001011011010001 3
b1110100100110000 2
b10011111111000010 1
b111011010110010 0
b1 /
b1100100100010000 $
b1100100100010000 )
b1100100100010000 .
b110110010010001011 !
b110110010010001011 +
b110110010010001011 4
1&
#1815000
0&
#1820000
b1 (
#1825000
b11111010110111 0
b10 /
b10011111111000010 $
b10011111111000010 )
b10011111111000010 .
b110001011011010001 !
b110001011011010001 +
b110001011011010001 4
b1110100100110000 #
b1110100100110000 *
b1110100100110000 -
1&
#1835000
0&
#1840000
b10 (
#1845000
b111111111011 0
b11 /
1&
#1855000
0&
#1860000
b11 (
#1865000
b1111111010110 0
b100 /
1&
#1875000
0&
#1880000
b100 (
#1885000
b11111111111 0
b101 /
1&
#1895000
0&
#1900000
b101 (
#1905000
b10000000000 0
b110 /
1&
#1915000
0&
#1920000
b110 (
#1925000
b1000000000 0
b111 /
1&
#1935000
0&
#1940000
b111 (
#1945000
b100000000 0
b1000 /
1&
#1955000
0&
#1960000
b1000 (
#1965000
b10000000 0
b1001 /
1&
#1975000
0&
#1980000
b1001 (
#1985000
b1000000 0
b1010 /
1&
#1995000
0&
#2000000
b1010 (
#2005000
b100000 0
b1011 /
1&
#2015000
0&
#2020000
b1011 (
#2025000
b10000 0
b1100 /
1&
#2035000
0&
#2040000
b1100 (
#2045000
b1000 0
b1101 /
1&
#2055000
0&
#2060000
b1101 (
#2065000
b100 0
b1110 /
1&
#2075000
0&
#2080000
b1110 (
#2085000
b10 0
b1111 /
1&
#2095000
0&
#2100000
b1111 (
#2105000
b1100100100010000 0
b0 /
1"
15
1&
#2115000
0&
#2120000
b10000 (
#2225000
b100110110111100000 %
b100110110111100000 ,
b100110110111100000 6
b10000000000000000 :
b11111111111111111111111111111110 9
b11111111111111100110110111011111 8
b100110110111100000 7
#2230000
b0 (
1'
#2235000
b0 !
b0 +
b0 4
b1001101101110101 #
b1001101101110101 *
b1001101101110101 -
b0 $
b0 )
b0 .
0"
05
1&
#2240000
0'
#2245000
0&
#2250000
b111011010110010 0
b1 /
b10011111111000010 $
b10011111111000010 )
b10011111111000010 .
b110001011011010001 !
b110001011011010001 +
b110001011011010001 4
b1110100100110000 #
b1110100100110000 *
b1110100100110000 -
1&
#2260000
0&
#2265000
b1 (
#2270000
b11111010110111 0
b10 /
1&
#2280000
0&
#2285000
b10 (
#2290000
b111111111011 0
b11 /
1&
#2300000
0&
#2305000
b11 (
#2310000
b1111111010110 0
b100 /
1&
#2320000
0&
#2325000
b100 (
#2330000
b11111111111 0
b101 /
1&
#2340000
0&
#2345000
b101 (
#2350000
b10000000000 0
b110 /
1&
#2360000
0&
#2365000
b110 (
#2370000
b1000000000 0
b111 /
1&
#2380000
0&
#2385000
b111 (
#2390000
b100000000 0
b1000 /
1&
#2400000
0&
#2405000
b1000 (
#2410000
b10000000 0
b1001 /
1&
#2420000
0&
#2425000
b1001 (
#2430000
b1000000 0
b1010 /
1&
#2440000
0&
#2445000
b1010 (
#2450000
b100000 0
b1011 /
1&
#2460000
0&
#2465000
b1011 (
#2470000
b10000 0
b1100 /
1&
#2480000
0&
#2485000
b1100 (
#2490000
b1000 0
b1101 /
1&
#2500000
0&
#2505000
b1101 (
#2510000
b100 0
b1110 /
1&
#2520000
0&
#2525000
b1110 (
#2530000
b10 0
b1111 /
1&
#2540000
0&
#2545000
b1111 (
#2550000
b1100100100010000 0
b0 /
1"
15
1&
#2560000
0&
#2565000
b10000 (
#2670000
b110011011011110000 %
b110011011011110000 ,
b110011011011110000 6
b11111111111111110100101011111010 :
b1011010100000101 9
b11111111111111110011011011101111 8
b110011011011110000 7
#2675000
b0 (
1'
#2680000
b0 !
b0 +
b0 4
b1001101101110101 #
b1001101101110101 *
b1001101101110101 -
b0 $
b0 )
b0 .
0"
05
1&
#2685000
0'
#2690000
0&
#2695000
b111011010110010 0
b1 /
b10011111111000010 $
b10011111111000010 )
b10011111111000010 .
b110001011011010001 !
b110001011011010001 +
b110001011011010001 4
b1110100100110000 #
b1110100100110000 *
b1110100100110000 -
1&
#2705000
0&
#2710000
b1 (
#2715000
b11111010110111 0
b10 /
1&
#2725000
0&
#2730000
b10 (
#2735000
b111111111011 0
b11 /
1&
#2745000
0&
#2750000
b11 (
#2755000
b1111111010110 0
b100 /
1&
#2765000
0&
#2770000
b100 (
#2775000
b11111111111 0
b101 /
1&
#2785000
0&
#2790000
b101 (
#2795000
b10000000000 0
b110 /
1&
#2805000
0&
#2810000
b110 (
#2815000
b1000000000 0
b111 /
1&
#2825000
0&
#2830000
b111 (
#2835000
b100000000 0
b1000 /
1&
#2845000
0&
#2850000
b1000 (
#2855000
b10000000 0
b1001 /
1&
#2865000
0&
#2870000
b1001 (
#2875000
b1000000 0
b1010 /
1&
#2885000
0&
#2890000
b1010 (
#2895000
b100000 0
b1011 /
1&
#2905000
0&
#2910000
b1011 (
#2915000
b10000 0
b1100 /
1&
#2925000
0&
#2930000
b1100 (
#2935000
b1000 0
b1101 /
1&
#2945000
0&
#2950000
b1101 (
#2955000
b100 0
b1110 /
1&
#2965000
0&
#2970000
b1110 (
#2975000
b10 0
b1111 /
1&
#2985000
0&
#2990000
b1111 (
#2995000
b1100100100010000 0
b0 /
1"
15
1&
#3005000
0&
#3010000
b10000 (
